odoo/addons/account_bank_statement_import_online_paypal/README.rst
odoo/addons/account_bank_statement_import_online_paypal/__init__.py
odoo/addons/account_bank_statement_import_online_paypal/__manifest__.py
odoo/addons/account_bank_statement_import_online_paypal/i18n/account_bank_statement_import_online_paypal.pot
odoo/addons/account_bank_statement_import_online_paypal/models/__init__.py
odoo/addons/account_bank_statement_import_online_paypal/models/online_bank_statement_provider_paypal.py
odoo/addons/account_bank_statement_import_online_paypal/readme/CONFIGURE.rst
odoo/addons/account_bank_statement_import_online_paypal/readme/CONTRIBUTORS.rst
odoo/addons/account_bank_statement_import_online_paypal/readme/DESCRIPTION.rst
odoo/addons/account_bank_statement_import_online_paypal/readme/ROADMAP.rst
odoo/addons/account_bank_statement_import_online_paypal/readme/USAGE.rst
odoo/addons/account_bank_statement_import_online_paypal/static/description/icon.png
odoo/addons/account_bank_statement_import_online_paypal/static/description/index.html
odoo/addons/account_bank_statement_import_online_paypal/tests/__init__.py
odoo/addons/account_bank_statement_import_online_paypal/tests/test_account_bank_statement_import_online_paypal.py
odoo/addons/account_bank_statement_import_online_paypal/views/online_bank_statement_provider.xml
odoo12_addon_account_bank_statement_import_online_paypal-12.0.1.1.0.dist-info/METADATA
odoo12_addon_account_bank_statement_import_online_paypal-12.0.1.1.0.dist-info/WHEEL
odoo12_addon_account_bank_statement_import_online_paypal-12.0.1.1.0.dist-info/top_level.txt
odoo12_addon_account_bank_statement_import_online_paypal-12.0.1.1.0.dist-info/RECORD
